tablo/__init__.py
tablo/combinators.py
tablo/format.py
tablo/parse.py
tablo/serializers.py
tablo/table.py
tablo_fyi-0.4.5.dist-info/METADATA
tablo_fyi-0.4.5.dist-info/WHEEL
tablo_fyi-0.4.5.dist-info/top_level.txt
tablo_fyi-0.4.5.dist-info/RECORD
