Metadata-Version: 2.1
Name: tablo-fyi
Version: 0.4.5
Summary: A tabular data format that doesn't make you want to pull your hair out
Home-page: https://github.com/jotjotdotio/tablo
Author: Brendan Berg
Author-email: brendan@berg.industries
License: MIT
Platform: UNKNOWN
